cisco_anyconnect_cli/__init__.py
cisco_anyconnect_cli/cisco_anyconnect.py
cisco_anyconnect_cli/cli.py
cisco_anyconnect_cli-0.6.dist-info/LICENSE
cisco_anyconnect_cli-0.6.dist-info/METADATA
cisco_anyconnect_cli-0.6.dist-info/WHEEL
cisco_anyconnect_cli-0.6.dist-info/entry_points.txt
cisco_anyconnect_cli-0.6.dist-info/top_level.txt
cisco_anyconnect_cli-0.6.dist-info/RECORD
