Metadata-Version: 2.1
Name: cisco-anyconnect-cli
Version: 0.6
Summary: Cisco AnyConnect command line interface
Home-page: https://github.com/hacki11/cisco-anyconnect-cli
Author: Juergen Schmid
License: apache-2.0
Keywords: vpn,cisco,anyconnect,cli
Classifier: Intended Audience :: Developers
Classifier: Topic :: Software Development :: Build Tools
Classifier: License :: OSI Approved :: Apache Software License
Classifier: Programming Language :: Python :: 3
Classifier: Operating System :: Microsoft :: Windows
License-File: LICENSE
Requires-Dist: click
Requires-Dist: keepasshttp
